productor/__init__.py
productor/__version__.py
productor/productor.py
productor-0.1.1.dist-info/METADATA
productor-0.1.1.dist-info/WHEEL
productor-0.1.1.dist-info/licenses/LICENSE
productor-0.1.1.dist-info/RECORD
