Metadata-Version: 2.3
Name: productor
Version: 0.1.1
Summary: 简单创建一个可以自动探索子类并加载的工厂
Project-URL: Homepage, https://github.com/swxs/swxs-productor
Project-URL: Issues, https://github.com/swxs/swxs-productor/issues
Author-email: swxs <466565029@qq.com>
License-Expression: BSD-2-Clause
License-File: LICENSE
Classifier: Operating System :: OS Independent
Classifier: Programming Language :: Python :: 3
Requires-Python: >=3.8
